NixiangGongchengRumenZhinan/README.md
NixiangGongchengRumenZhinan/__init__.py
NixiangGongchengRumenZhinan/__main__.py
NixiangGongchengRumenZhinan/file.epub
NixiangGongchengRumenZhinan/index.html
NixiangGongchengRumenZhinan/css/__init__.py
NixiangGongchengRumenZhinan/css/annotations.css
NixiangGongchengRumenZhinan/css/main.css
NixiangGongchengRumenZhinan/css/normalize.css
NixiangGongchengRumenZhinan/css/popup.css
NixiangGongchengRumenZhinan/font/__init__.py
NixiangGongchengRumenZhinan/font/fontello.eot
NixiangGongchengRumenZhinan/font/fontello.svg
NixiangGongchengRumenZhinan/font/fontello.ttf
NixiangGongchengRumenZhinan/font/fontello.woff
NixiangGongchengRumenZhinan/img/__init__.py
NixiangGongchengRumenZhinan/img/annotator-glyph-sprite.png
NixiangGongchengRumenZhinan/img/annotator-icon-sprite.png
NixiangGongchengRumenZhinan/img/apple-touch-icon.png
NixiangGongchengRumenZhinan/img/cancelfullscreen.png
NixiangGongchengRumenZhinan/img/close.png
NixiangGongchengRumenZhinan/img/fullscreen.png
NixiangGongchengRumenZhinan/img/loader.gif
NixiangGongchengRumenZhinan/img/menu-icon.png
NixiangGongchengRumenZhinan/img/save.png
NixiangGongchengRumenZhinan/img/saved.png
NixiangGongchengRumenZhinan/img/settings-s.png
NixiangGongchengRumenZhinan/img/settings.png
NixiangGongchengRumenZhinan/img/star.png
NixiangGongchengRumenZhinan/js/__init__.py
NixiangGongchengRumenZhinan/js/epub.js
NixiangGongchengRumenZhinan/js/epub.min.js
NixiangGongchengRumenZhinan/js/epub.min.map
NixiangGongchengRumenZhinan/js/hooks.min.js
NixiangGongchengRumenZhinan/js/hooks.min.map
NixiangGongchengRumenZhinan/js/reader.js
NixiangGongchengRumenZhinan/js/reader.js.map
NixiangGongchengRumenZhinan/js/reader.min.js
NixiangGongchengRumenZhinan/js/reader.min.map
NixiangGongchengRumenZhinan/js/hooks/__init__.py
NixiangGongchengRumenZhinan/js/hooks/extensions/__init__.py
NixiangGongchengRumenZhinan/js/hooks/extensions/highlight.js
NixiangGongchengRumenZhinan/js/libs/__init__.py
nixiang_gongcheng_rumen_zhinan-2024.3.2.0.dist-info/METADATA
nixiang_gongcheng_rumen_zhinan-2024.3.2.0.dist-info/WHEEL
nixiang_gongcheng_rumen_zhinan-2024.3.2.0.dist-info/entry_points.txt
nixiang_gongcheng_rumen_zhinan-2024.3.2.0.dist-info/top_level.txt
nixiang_gongcheng_rumen_zhinan-2024.3.2.0.dist-info/RECORD
